pycounts_ik2025/__init__.py
pycounts_ik2025/plotting.py
pycounts_ik2025/pycounts_ik2025.py
pycounts_ik2025-0.1.0.dist-info/LICENSE
pycounts_ik2025-0.1.0.dist-info/METADATA
pycounts_ik2025-0.1.0.dist-info/WHEEL
pycounts_ik2025-0.1.0.dist-info/RECORD
